message_queue_sqlite/__init__.py
message_queue_sqlite/cache/__init__.py
message_queue_sqlite/config/__init__.py
message_queue_sqlite/constants/__init__.py
message_queue_sqlite/constants/task_status.py
message_queue_sqlite/middleware/__init__.py
message_queue_sqlite/middleware/client.py
message_queue_sqlite/middleware/server.py
message_queue_sqlite/model/__init__.py
message_queue_sqlite/model/task_resutl.py
message_queue_sqlite/model/thread_dict.py
message_queue_sqlite/model/thread_set.py
message_queue_sqlite/task_service/__init__.py
message_queue_sqlite/task_service/service/__init__.py
message_queue_sqlite/task_service/service/services.py
message_queue_sqlite/task_service/task/__init__.py
message_queue_sqlite/task_service/task/discover.py
message_queue_sqlite/task_service/task/task_base.py
message_queue_sqlite/task_service/task/tasks.py
message_queue_sqlite-2.0.1.dist-info/LICENSE
message_queue_sqlite-2.0.1.dist-info/METADATA
message_queue_sqlite-2.0.1.dist-info/WHEEL
message_queue_sqlite-2.0.1.dist-info/top_level.txt
message_queue_sqlite-2.0.1.dist-info/RECORD
