Metadata-Version: 2.1
Name: message-queue-sqlite
Version: 2.0.1
Summary: A simple message queue demo
Home-page: https://gitee.com/cai-xinpenge/message_queue
Author: chakcy
Author-email: 947105045@qq.com
License: UNKNOWN
Platform: UNKNOWN
Classifier: Programming Language :: Python :: 3
Classifier: License :: OSI Approved :: MIT License
Classifier: Operating System :: OS Independent
Requires-Python: >=3.8
